ccinit.py
ccinit-0.1.8.dist-info/licenses/LICENCE.md
ccinit-0.1.8.dist-info/licenses/LICENSE
ccinit-0.1.8.dist-info/licenses/LICENSE.txt
ccinit-0.1.8.dist-info/METADATA
ccinit-0.1.8.dist-info/WHEEL
ccinit-0.1.8.dist-info/entry_points.txt
ccinit-0.1.8.dist-info/top_level.txt
ccinit-0.1.8.dist-info/RECORD
