Metadata-Version: 2.4
Name: ccinit
Version: 0.1.8
Summary: Fetches and inlines remote C include dependencies
Author: Gabriel Belão Kaminski
License: MIT License
Requires-Python: >=3.8
License-File: LICENCE.md
License-File: LICENSE
License-File: LICENSE.txt
Dynamic: license-file
